streamlit_code_diff/__init__.py
streamlit_code_diff/frontend/index.html
streamlit_code_diff/frontend/package-lock.json
streamlit_code_diff/frontend/package.json
streamlit_code_diff/frontend/tsconfig.json
streamlit_code_diff/frontend/tsconfig.node.json
streamlit_code_diff/frontend/vite.config.ts
streamlit_code_diff/frontend/build/bundle.css
streamlit_code_diff/frontend/build/bundle.js
streamlit_code_diff/frontend/build/index.html
streamlit_code_diff/frontend/src/StreamlitCodeDiff.vue
streamlit_code_diff/frontend/src/index.css
streamlit_code_diff/frontend/src/main.ts
streamlit_code_diff-0.1.2.dist-info/METADATA
streamlit_code_diff-0.1.2.dist-info/WHEEL
streamlit_code_diff-0.1.2.dist-info/licenses/LICENSE
streamlit_code_diff-0.1.2.dist-info/RECORD
