Metadata-Version: 2.4
Name: streamlit-code-diff
Version: 0.1.2
Summary: A Streamlit component for code diff visualization using v-code-diff
Project-URL: Homepage, https://github.com/evertoncolling/streamlit-code-diff
Project-URL: Repository, https://github.com/evertoncolling/streamlit-code-diff
Project-URL: Issues, https://github.com/evertoncolling/streamlit-code-diff/issues
Author-email: Everton Colling <evertoncolling@gmail.com>
License-Expression: MIT
License-File: LICENSE
Keywords: code-diff,component,diff,streamlit,visualization
Classifier: Development Status :: 4 - Beta
Classifier: Intended Audience :: Developers
Classifier: License :: OSI Approved :: MIT License
Classifier: Programming Language :: Python :: 3
Classifier: Programming Language :: Python :: 3.9
Classifier: Programming Language :: Python :: 3.10
Classifier: Programming Language :: Python :: 3.11
Classifier: Programming Language :: Python :: 3.12
Classifier: Topic :: Software Development :: Libraries :: Python Modules
Requires-Python: >=3.9
Requires-Dist: numpy>=1.24.4; python_version < '3.12'
Requires-Dist: numpy>=1.26.0; python_version >= '3.12'
Requires-Dist: streamlit>=1.28.0
